[
    {
        "Command":  "Resume-AzureRmAnalysisServicesServer",
        "IsAlias":  false,
        "SourceModule":  "AzureRM.AnalysisServices",
        "Version":  "0.6.14",
        "Parameters":  [
                           {
                               "Name":  "ResourceGroupName",
                               "Aliases":  null
                           },
                           {
                               "Name":  "Name",
                               "Aliases":  null
                           },
                           {
                               "Name":  "PassThru",
                               "Aliases":  null
                           },
                           {
                               "Name":  "DefaultProfile",
                               "Aliases":  [
                                               "AzureRmContext",
                                               "AzureCredential"
                                           ]
                           },
                           {
                               "Name":  "WhatIf",
                               "Aliases":  [
                                               "wi"
                                           ]
                           },
                           {
                               "Name":  "Confirm",
                               "Aliases":  [
                                               "cf"
                                           ]
                           }
                       ]
    },
    {
        "Command":  "Suspend-AzureRmAnalysisServicesServer",
        "IsAlias":  false,
        "SourceModule":  "AzureRM.AnalysisServices",
        "Version":  "0.6.14",
        "Parameters":  [
                           {
                               "Name":  "ResourceGroupName",
                               "Aliases":  null
                           },
                           {
                               "Name":  "Name",
                               "Aliases":  null
                           },
                           {
                               "Name":  "PassThru",
                               "Aliases":  null
                           },
                           {
                               "Name":  "DefaultProfile",
                               "Aliases":  [
                                               "AzureRmContext",
                                               "AzureCredential"
                                           ]
                           },
                           {
                               "Name":  "WhatIf",
                               "Aliases":  [
                                               "wi"
                                           ]
                           },
                           {
                               "Name":  "Confirm",
                               "Aliases":  [
                                               "cf"
                                           ]
                           }
                       ]
    },
    {
        "Command":  "Get-AzureRmAnalysisServicesServer",
        "IsAlias":  false,
        "SourceModule":  "AzureRM.AnalysisServices",
        "Version":  "0.6.14",
        "Parameters":  [
                           {
                               "Name":  "ResourceGroupName",
                               "Aliases":  null
                           },
                           {
                               "Name":  "Name",
                               "Aliases":  null
                           },
                           {
                               "Name":  "DefaultProfile",
                               "Aliases":  [
                                               "AzureRmContext",
                                               "AzureCredential"
                                           ]
                           }
                       ]
    },
    {
        "Command":  "Remove-AzureRmAnalysisServicesServer",
        "IsAlias":  false,
        "SourceModule":  "AzureRM.AnalysisServices",
        "Version":  "0.6.14",
        "Parameters":  [
                           {
                               "Name":  "Name",
                               "Aliases":  null
                           },
                           {
                               "Name":  "ResourceGroupName",
                               "Aliases":  null
                           },
                           {
                               "Name":  "PassThru",
                               "Aliases":  null
                           },
                           {
                               "Name":  "DefaultProfile",
                               "Aliases":  [
                                               "AzureRmContext",
                                               "AzureCredential"
                                           ]
                           },
                           {
                               "Name":  "WhatIf",
                               "Aliases":  [
                                               "wi"
                                           ]
                           },
                           {
                               "Name":  "Confirm",
                               "Aliases":  [
                                               "cf"
                                           ]
                           }
                       ]
    },
    {
        "Command":  "Set-AzureRmAnalysisServicesServer",
        "IsAlias":  false,
        "SourceModule":  "AzureRM.AnalysisServices",
        "Version":  "0.6.14",
        "Parameters":  [
                           {
                               "Name":  "Name",
                               "Aliases":  null
                           },
                           {
                               "Name":  "ResourceGroupName",
                               "Aliases":  null
                           },
                           {
                               "Name":  "Sku",
                               "Aliases":  null
                           },
                           {
                               "Name":  "Tag",
                               "Aliases":  null
                           },
                           {
                               "Name":  "Administrator",
                               "Aliases":  null
                           },
                           {
                               "Name":  "BackupBlobContainerUri",
                               "Aliases":  null
                           },
                           {
                               "Name":  "PassThru",
                               "Aliases":  null
                           },
                           {
                               "Name":  "DisableBackup",
                               "Aliases":  null
                           },
                           {
                               "Name":  "ReadonlyReplicaCount",
                               "Aliases":  null
                           },
                           {
                               "Name":  "DefaultConnectionMode",
                               "Aliases":  null
                           },
                           {
                               "Name":  "FirewallConfig",
                               "Aliases":  null
                           },
                           {
                               "Name":  "GatewayResourceId",
                               "Aliases":  null
                           },
                           {
                               "Name":  "DisassociateGateway",
                               "Aliases":  null
                           },
                           {
                               "Name":  "DefaultProfile",
                               "Aliases":  [
                                               "AzureRmContext",
                                               "AzureCredential"
                                           ]
                           },
                           {
                               "Name":  "WhatIf",
                               "Aliases":  [
                                               "wi"
                                           ]
                           },
                           {
                               "Name":  "Confirm",
                               "Aliases":  [
                                               "cf"
                                           ]
                           }
                       ]
    },
    {
        "Command":  "Test-AzureRmAnalysisServicesServer",
        "IsAlias":  false,
        "SourceModule":  "AzureRM.AnalysisServices",
        "Version":  "0.6.14",
        "Parameters":  [
                           {
                               "Name":  "Name",
                               "Aliases":  null
                           },
                           {
                               "Name":  "ResourceGroupName",
                               "Aliases":  null
                           },
                           {
                               "Name":  "DefaultProfile",
                               "Aliases":  [
                                               "AzureRmContext",
                                               "AzureCredential"
                                           ]
                           }
                       ]
    },
    {
        "Command":  "New-AzureRmAnalysisServicesServer",
        "IsAlias":  false,
        "SourceModule":  "AzureRM.AnalysisServices",
        "Version":  "0.6.14",
        "Parameters":  [
                           {
                               "Name":  "ResourceGroupName",
                               "Aliases":  null
                           },
                           {
                               "Name":  "Name",
                               "Aliases":  null
                           },
                           {
                               "Name":  "Location",
                               "Aliases":  null
                           },
                           {
                               "Name":  "Sku",
                               "Aliases":  null
                           },
                           {
                               "Name":  "Tag",
                               "Aliases":  null
                           },
                           {
                               "Name":  "Administrator",
                               "Aliases":  null
                           },
                           {
                               "Name":  "BackupBlobContainerUri",
                               "Aliases":  null
                           },
                           {
                               "Name":  "ReadonlyReplicaCount",
                               "Aliases":  null
                           },
                           {
                               "Name":  "DefaultConnectionMode",
                               "Aliases":  null
                           },
                           {
                               "Name":  "FirewallConfig",
                               "Aliases":  null
                           },
                           {
                               "Name":  "GatewayResourceId",
                               "Aliases":  null
                           },
                           {
                               "Name":  "DefaultProfile",
                               "Aliases":  [
                                               "AzureRmContext",
                                               "AzureCredential"
                                           ]
                           },
                           {
                               "Name":  "WhatIf",
                               "Aliases":  [
                                               "wi"
                                           ]
                           },
                           {
                               "Name":  "Confirm",
                               "Aliases":  [
                                               "cf"
                                           ]
                           }
                       ]
    },
    {
        "Command":  "New-AzureRmAnalysisServicesFirewallRule",
        "IsAlias":  false,
        "SourceModule":  "AzureRM.AnalysisServices",
        "Version":  "0.6.14",
        "Parameters":  [
                           {
                               "Name":  "FirewallRuleName",
                               "Aliases":  null
                           },
                           {
                               "Name":  "RangeStart",
                               "Aliases":  null
                           },
                           {
                               "Name":  "RangeEnd",
                               "Aliases":  null
                           },
                           {
                               "Name":  "DefaultProfile",
                               "Aliases":  [
                                               "AzureRmContext",
                                               "AzureCredential"
                                           ]
                           }
                       ]
    },
    {
        "Command":  "New-AzureRmAnalysisServicesFirewallConfig",
        "IsAlias":  false,
        "SourceModule":  "AzureRM.AnalysisServices",
        "Version":  "0.6.14",
        "Parameters":  [
                           {
                               "Name":  "EnablePowerBIService",
                               "Aliases":  null
                           },
                           {
                               "Name":  "FirewallRule",
                               "Aliases":  null
                           },
                           {
                               "Name":  "DefaultProfile",
                               "Aliases":  [
                                               "AzureRmContext",
                                               "AzureCredential"
                                           ]
                           }
                       ]
    },
    {
        "Command":  "Resume-AzureAs",
        "IsAlias":  false,
        "SourceModule":  "AzureRM.AnalysisServices",
        "Version":  "0.6.14",
        "Parameters":  [
                           {
                               "Name":  "ResourceGroupName",
                               "Aliases":  null
                           },
                           {
                               "Name":  "Name",
                               "Aliases":  null
                           },
                           {
                               "Name":  "PassThru",
                               "Aliases":  null
                           },
                           {
                               "Name":  "DefaultProfile",
                               "Aliases":  [
                                               "AzureRmContext",
                                               "AzureCredential"
                                           ]
                           },
                           {
                               "Name":  "WhatIf",
                               "Aliases":  [
                                               "wi"
                                           ]
                           },
                           {
                               "Name":  "Confirm",
                               "Aliases":  [
                                               "cf"
                                           ]
                           }
                       ]
    },
    {
        "Command":  "Suspend-AzureAs",
        "IsAlias":  false,
        "SourceModule":  "AzureRM.AnalysisServices",
        "Version":  "0.6.14",
        "Parameters":  [
                           {
                               "Name":  "ResourceGroupName",
                               "Aliases":  null
                           },
                           {
                               "Name":  "Name",
                               "Aliases":  null
                           },
                           {
                               "Name":  "PassThru",
                               "Aliases":  null
                           },
                           {
                               "Name":  "DefaultProfile",
                               "Aliases":  [
                                               "AzureRmContext",
                                               "AzureCredential"
                                           ]
                           },
                           {
                               "Name":  "WhatIf",
                               "Aliases":  [
                                               "wi"
                                           ]
                           },
                           {
                               "Name":  "Confirm",
                               "Aliases":  [
                                               "cf"
                                           ]
                           }
                       ]
    },
    {
        "Command":  "Get-AzureAs",
        "IsAlias":  false,
        "SourceModule":  "AzureRM.AnalysisServices",
        "Version":  "0.6.14",
        "Parameters":  [
                           {
                               "Name":  "ResourceGroupName",
                               "Aliases":  null
                           },
                           {
                               "Name":  "Name",
                               "Aliases":  null
                           },
                           {
                               "Name":  "DefaultProfile",
                               "Aliases":  [
                                               "AzureRmContext",
                                               "AzureCredential"
                                           ]
                           }
                       ]
    },
    {
        "Command":  "Remove-AzureAs",
        "IsAlias":  false,
        "SourceModule":  "AzureRM.AnalysisServices",
        "Version":  "0.6.14",
        "Parameters":  [
                           {
                               "Name":  "Name",
                               "Aliases":  null
                           },
                           {
                               "Name":  "ResourceGroupName",
                               "Aliases":  null
                           },
                           {
                               "Name":  "PassThru",
                               "Aliases":  null
                           },
                           {
                               "Name":  "DefaultProfile",
                               "Aliases":  [
                                               "AzureRmContext",
                                               "AzureCredential"
                                           ]
                           },
                           {
                               "Name":  "WhatIf",
                               "Aliases":  [
                                               "wi"
                                           ]
                           },
                           {
                               "Name":  "Confirm",
                               "Aliases":  [
                                               "cf"
                                           ]
                           }
                       ]
    },
    {
        "Command":  "Set-AzureAs",
        "IsAlias":  false,
        "SourceModule":  "AzureRM.AnalysisServices",
        "Version":  "0.6.14",
        "Parameters":  [
                           {
                               "Name":  "Name",
                               "Aliases":  null
                           },
                           {
                               "Name":  "ResourceGroupName",
                               "Aliases":  null
                           },
                           {
                               "Name":  "Sku",
                               "Aliases":  null
                           },
                           {
                               "Name":  "Tag",
                               "Aliases":  null
                           },
                           {
                               "Name":  "Administrator",
                               "Aliases":  null
                           },
                           {
                               "Name":  "BackupBlobContainerUri",
                               "Aliases":  null
                           },
                           {
                               "Name":  "PassThru",
                               "Aliases":  null
                           },
                           {
                               "Name":  "DisableBackup",
                               "Aliases":  null
                           },
                           {
                               "Name":  "ReadonlyReplicaCount",
                               "Aliases":  null
                           },
                           {
                               "Name":  "DefaultConnectionMode",
                               "Aliases":  null
                           },
                           {
                               "Name":  "FirewallConfig",
                               "Aliases":  null
                           },
                           {
                               "Name":  "GatewayResourceId",
                               "Aliases":  null
                           },
                           {
                               "Name":  "DisassociateGateway",
                               "Aliases":  null
                           },
                           {
                               "Name":  "DefaultProfile",
                               "Aliases":  [
                                               "AzureRmContext",
                                               "AzureCredential"
                                           ]
                           },
                           {
                               "Name":  "WhatIf",
                               "Aliases":  [
                                               "wi"
                                           ]
                           },
                           {
                               "Name":  "Confirm",
                               "Aliases":  [
                                               "cf"
                                           ]
                           }
                       ]
    },
    {
        "Command":  "Test-AzureAs",
        "IsAlias":  false,
        "SourceModule":  "AzureRM.AnalysisServices",
        "Version":  "0.6.14",
        "Parameters":  [
                           {
                               "Name":  "Name",
                               "Aliases":  null
                           },
                           {
                               "Name":  "ResourceGroupName",
                               "Aliases":  null
                           },
                           {
                               "Name":  "DefaultProfile",
                               "Aliases":  [
                                               "AzureRmContext",
                                               "AzureCredential"
                                           ]
                           }
                       ]
    },
    {
        "Command":  "New-AzureAs",
        "IsAlias":  false,
        "SourceModule":  "AzureRM.AnalysisServices",
        "Version":  "0.6.14",
        "Parameters":  [
                           {
                               "Name":  "ResourceGroupName",
                               "Aliases":  null
                           },
                           {
                               "Name":  "Name",
                               "Aliases":  null
                           },
                           {
                               "Name":  "Location",
                               "Aliases":  null
                           },
                           {
                               "Name":  "Sku",
                               "Aliases":  null
                           },
                           {
                               "Name":  "Tag",
                               "Aliases":  null
                           },
                           {
                               "Name":  "Administrator",
                               "Aliases":  null
                           },
                           {
                               "Name":  "BackupBlobContainerUri",
                               "Aliases":  null
                           },
                           {
                               "Name":  "ReadonlyReplicaCount",
                               "Aliases":  null
                           },
                           {
                               "Name":  "DefaultConnectionMode",
                               "Aliases":  null
                           },
                           {
                               "Name":  "FirewallConfig",
                               "Aliases":  null
                           },
                           {
                               "Name":  "GatewayResourceId",
                               "Aliases":  null
                           },
                           {
                               "Name":  "DefaultProfile",
                               "Aliases":  [
                                               "AzureRmContext",
                                               "AzureCredential"
                                           ]
                           },
                           {
                               "Name":  "WhatIf",
                               "Aliases":  [
                                               "wi"
                                           ]
                           },
                           {
                               "Name":  "Confirm",
                               "Aliases":  [
                                               "cf"
                                           ]
                           }
                       ]
    }
]
