[
  {
    "Command": "Get-AzCdnProfile",
    "IsAlias": false,
    "SourceModule": "Az.Cdn",
    "Version": "1.6.0",
    "Parameters": [
      {
        "Name": "ProfileName",
        "Aliases": null
      },
      {
        "Name": "ResourceGroupName",
        "Aliases": null
      },
      {
        "Name": "DefaultProfile",
        "Aliases": [
          "AzContext",
          "AzureRmContext",
          "AzureCredential"
        ]
      }
    ]
  },
  {
    "Command": "Get-AzCdnProfileSsoUrl",
    "IsAlias": false,
    "SourceModule": "Az.Cdn",
    "Version": "1.6.0",
    "Parameters": [
      {
        "Name": "ProfileName",
        "Aliases": null
      },
      {
        "Name": "ResourceGroupName",
        "Aliases": null
      },
      {
        "Name": "CdnProfile",
        "Aliases": null
      },
      {
        "Name": "DefaultProfile",
        "Aliases": [
          "AzContext",
          "AzureRmContext",
          "AzureCredential"
        ]
      }
    ]
  },
  {
    "Command": "New-AzCdnProfile",
    "IsAlias": false,
    "SourceModule": "Az.Cdn",
    "Version": "1.6.0",
    "Parameters": [
      {
        "Name": "ProfileName",
        "Aliases": null
      },
      {
        "Name": "Location",
        "Aliases": null
      },
      {
        "Name": "Sku",
        "Aliases": null
      },
      {
        "Name": "ResourceGroupName",
        "Aliases": null
      },
      {
        "Name": "Tag",
        "Aliases": null
      },
      {
        "Name": "DefaultProfile",
        "Aliases": [
          "AzContext",
          "AzureRmContext",
          "AzureCredential"
        ]
      },
      {
        "Name": "WhatIf",
        "Aliases": [
          "wi"
        ]
      },
      {
        "Name": "Confirm",
        "Aliases": [
          "cf"
        ]
      }
    ]
  },
  {
    "Command": "Remove-AzCdnProfile",
    "IsAlias": false,
    "SourceModule": "Az.Cdn",
    "Version": "1.6.0",
    "Parameters": [
      {
        "Name": "ProfileName",
        "Aliases": null
      },
      {
        "Name": "ResourceGroupName",
        "Aliases": null
      },
      {
        "Name": "CdnProfile",
        "Aliases": null
      },
      {
        "Name": "PassThru",
        "Aliases": null
      },
      {
        "Name": "Force",
        "Aliases": null
      },
      {
        "Name": "DefaultProfile",
        "Aliases": [
          "AzContext",
          "AzureRmContext",
          "AzureCredential"
        ]
      },
      {
        "Name": "WhatIf",
        "Aliases": [
          "wi"
        ]
      },
      {
        "Name": "Confirm",
        "Aliases": [
          "cf"
        ]
      }
    ]
  },
  {
    "Command": "Set-AzCdnProfile",
    "IsAlias": false,
    "SourceModule": "Az.Cdn",
    "Version": "1.6.0",
    "Parameters": [
      {
        "Name": "CdnProfile",
        "Aliases": null
      },
      {
        "Name": "DefaultProfile",
        "Aliases": [
          "AzContext",
          "AzureRmContext",
          "AzureCredential"
        ]
      },
      {
        "Name": "WhatIf",
        "Aliases": [
          "wi"
        ]
      },
      {
        "Name": "Confirm",
        "Aliases": [
          "cf"
        ]
      }
    ]
  },
  {
    "Command": "Get-AzCdnOrigin",
    "IsAlias": false,
    "SourceModule": "Az.Cdn",
    "Version": "1.6.0",
    "Parameters": [
      {
        "Name": "OriginName",
        "Aliases": null
      },
      {
        "Name": "EndpointName",
        "Aliases": null
      },
      {
        "Name": "ProfileName",
        "Aliases": null
      },
      {
        "Name": "ResourceGroupName",
        "Aliases": null
      },
      {
        "Name": "ResourceId",
        "Aliases": null
      },
      {
        "Name": "CdnEndpoint",
        "Aliases": null
      },
      {
        "Name": "DefaultProfile",
        "Aliases": [
          "AzContext",
          "AzureRmContext",
          "AzureCredential"
        ]
      }
    ]
  },
  {
    "Command": "Set-AzCdnOrigin",
    "IsAlias": false,
    "SourceModule": "Az.Cdn",
    "Version": "1.6.0",
    "Parameters": [
      {
        "Name": "EndpointName",
        "Aliases": null
      },
      {
        "Name": "HostName",
        "Aliases": null
      },
      {
        "Name": "HttpPort",
        "Aliases": null
      },
      {
        "Name": "HttpsPort",
        "Aliases": null
      },
      {
        "Name": "OriginHostHeader",
        "Aliases": null
      },
      {
        "Name": "OriginName",
        "Aliases": null
      },
      {
        "Name": "ProfileName",
        "Aliases": null
      },
      {
        "Name": "Priority",
        "Aliases": null
      },
      {
        "Name": "PrivateLinkApprovalMessage",
        "Aliases": null
      },
      {
        "Name": "PrivateLinkLocation",
        "Aliases": null
      },
      {
        "Name": "PrivateLinkResourceId",
        "Aliases": null
      },
      {
        "Name": "ResourceGroupName",
        "Aliases": null
      },
      {
        "Name": "Weight",
        "Aliases": null
      },
      {
        "Name": "CdnOrigin",
        "Aliases": null
      },
      {
        "Name": "DefaultProfile",
        "Aliases": [
          "AzContext",
          "AzureRmContext",
          "AzureCredential"
        ]
      },
      {
        "Name": "WhatIf",
        "Aliases": [
          "wi"
        ]
      },
      {
        "Name": "Confirm",
        "Aliases": [
          "cf"
        ]
      }
    ]
  },
  {
    "Command": "Get-AzCdnEndpointNameAvailability",
    "IsAlias": false,
    "SourceModule": "Az.Cdn",
    "Version": "1.6.0",
    "Parameters": [
      {
        "Name": "EndpointName",
        "Aliases": null
      },
      {
        "Name": "DefaultProfile",
        "Aliases": [
          "AzContext",
          "AzureRmContext",
          "AzureCredential"
        ]
      }
    ]
  },
  {
    "Command": "Get-AzCdnEndpoint",
    "IsAlias": false,
    "SourceModule": "Az.Cdn",
    "Version": "1.6.0",
    "Parameters": [
      {
        "Name": "EndpointName",
        "Aliases": null
      },
      {
        "Name": "ProfileName",
        "Aliases": null
      },
      {
        "Name": "ResourceGroupName",
        "Aliases": null
      },
      {
        "Name": "CdnProfile",
        "Aliases": null
      },
      {
        "Name": "DefaultProfile",
        "Aliases": [
          "AzContext",
          "AzureRmContext",
          "AzureCredential"
        ]
      }
    ]
  },
  {
    "Command": "Publish-AzCdnEndpointContent",
    "IsAlias": false,
    "SourceModule": "Az.Cdn",
    "Version": "1.6.0",
    "Parameters": [
      {
        "Name": "EndpointName",
        "Aliases": null
      },
      {
        "Name": "ProfileName",
        "Aliases": null
      },
      {
        "Name": "ResourceGroupName",
        "Aliases": null
      },
      {
        "Name": "CdnEndpoint",
        "Aliases": null
      },
      {
        "Name": "LoadContent",
        "Aliases": null
      },
      {
        "Name": "PassThru",
        "Aliases": null
      },
      {
        "Name": "DefaultProfile",
        "Aliases": [
          "AzContext",
          "AzureRmContext",
          "AzureCredential"
        ]
      }
    ]
  },
  {
    "Command": "New-AzCdnEndpoint",
    "IsAlias": false,
    "SourceModule": "Az.Cdn",
    "Version": "1.6.0",
    "Parameters": [
      {
        "Name": "EndpointName",
        "Aliases": null
      },
      {
        "Name": "ProfileName",
        "Aliases": null
      },
      {
        "Name": "ResourceGroupName",
        "Aliases": null
      },
      {
        "Name": "CdnProfile",
        "Aliases": null
      },
      {
        "Name": "Location",
        "Aliases": null
      },
      {
        "Name": "OriginHostHeader",
        "Aliases": null
      },
      {
        "Name": "OriginPath",
        "Aliases": null
      },
      {
        "Name": "ContentTypesToCompress",
        "Aliases": null
      },
      {
        "Name": "IsCompressionEnabled",
        "Aliases": null
      },
      {
        "Name": "IsHttpAllowed",
        "Aliases": null
      },
      {
        "Name": "IsHttpsAllowed",
        "Aliases": null
      },
      {
        "Name": "QueryStringCachingBehavior",
        "Aliases": null
      },
      {
        "Name": "OriginName",
        "Aliases": null
      },
      {
        "Name": "OriginHostName",
        "Aliases": null
      },
      {
        "Name": "HttpPort",
        "Aliases": null
      },
      {
        "Name": "HttpsPort",
        "Aliases": null
      },
      {
        "Name": "OptimizationType",
        "Aliases": null
      },
      {
        "Name": "ProbePath",
        "Aliases": null
      },
      {
        "Name": "GeoFilters",
        "Aliases": null
      },
      {
        "Name": "DeliveryPolicy",
        "Aliases": null
      },
      {
        "Name": "Tag",
        "Aliases": null
      },
      {
        "Name": "DefaultOriginGroup",
        "Aliases": null
      },
      {
        "Name": "Priority",
        "Aliases": null
      },
      {
        "Name": "Weight",
        "Aliases": null
      },
      {
        "Name": "PrivateLinkApprovalMessage",
        "Aliases": null
      },
      {
        "Name": "PrivateLinkLocation",
        "Aliases": null
      },
      {
        "Name": "PrivateLinkResourceId",
        "Aliases": null
      },
      {
        "Name": "OriginId",
        "Aliases": null
      },
      {
        "Name": "OriginGroupName",
        "Aliases": null
      },
      {
        "Name": "OriginGroupProbeIntervalInSeconds",
        "Aliases": null
      },
      {
        "Name": "OriginGroupProbePath",
        "Aliases": null
      },
      {
        "Name": "OriginGroupProbeProtocol",
        "Aliases": null
      },
      {
        "Name": "OriginGroupProbeRequestType",
        "Aliases": null
      },
      {
        "Name": "DefaultProfile",
        "Aliases": [
          "AzContext",
          "AzureRmContext",
          "AzureCredential"
        ]
      },
      {
        "Name": "WhatIf",
        "Aliases": [
          "wi"
        ]
      },
      {
        "Name": "Confirm",
        "Aliases": [
          "cf"
        ]
      }
    ]
  },
  {
    "Command": "Unpublish-AzCdnEndpointContent",
    "IsAlias": false,
    "SourceModule": "Az.Cdn",
    "Version": "1.6.0",
    "Parameters": [
      {
        "Name": "EndpointName",
        "Aliases": null
      },
      {
        "Name": "ProfileName",
        "Aliases": null
      },
      {
        "Name": "ResourceGroupName",
        "Aliases": null
      },
      {
        "Name": "CdnEndpoint",
        "Aliases": null
      },
      {
        "Name": "PurgeContent",
        "Aliases": null
      },
      {
        "Name": "PassThru",
        "Aliases": null
      },
      {
        "Name": "DefaultProfile",
        "Aliases": [
          "AzContext",
          "AzureRmContext",
          "AzureCredential"
        ]
      },
      {
        "Name": "WhatIf",
        "Aliases": [
          "wi"
        ]
      },
      {
        "Name": "Confirm",
        "Aliases": [
          "cf"
        ]
      }
    ]
  },
  {
    "Command": "Remove-AzCdnEndpoint",
    "IsAlias": false,
    "SourceModule": "Az.Cdn",
    "Version": "1.6.0",
    "Parameters": [
      {
        "Name": "EndpointName",
        "Aliases": null
      },
      {
        "Name": "ProfileName",
        "Aliases": null
      },
      {
        "Name": "ResourceGroupName",
        "Aliases": null
      },
      {
        "Name": "CdnEndpoint",
        "Aliases": null
      },
      {
        "Name": "PassThru",
        "Aliases": null
      },
      {
        "Name": "Force",
        "Aliases": null
      },
      {
        "Name": "DefaultProfile",
        "Aliases": [
          "AzContext",
          "AzureRmContext",
          "AzureCredential"
        ]
      },
      {
        "Name": "WhatIf",
        "Aliases": [
          "wi"
        ]
      },
      {
        "Name": "Confirm",
        "Aliases": [
          "cf"
        ]
      }
    ]
  },
  {
    "Command": "Set-AzCdnEndpoint",
    "IsAlias": false,
    "SourceModule": "Az.Cdn",
    "Version": "1.6.0",
    "Parameters": [
      {
        "Name": "CdnEndpoint",
        "Aliases": null
      },
      {
        "Name": "DefaultProfile",
        "Aliases": [
          "AzContext",
          "AzureRmContext",
          "AzureCredential"
        ]
      },
      {
        "Name": "WhatIf",
        "Aliases": [
          "wi"
        ]
      },
      {
        "Name": "Confirm",
        "Aliases": [
          "cf"
        ]
      }
    ]
  },
  {
    "Command": "Start-AzCdnEndpoint",
    "IsAlias": false,
    "SourceModule": "Az.Cdn",
    "Version": "1.6.0",
    "Parameters": [
      {
        "Name": "EndpointName",
        "Aliases": null
      },
      {
        "Name": "ProfileName",
        "Aliases": null
      },
      {
        "Name": "ResourceGroupName",
        "Aliases": null
      },
      {
        "Name": "CdnEndpoint",
        "Aliases": null
      },
      {
        "Name": "PassThru",
        "Aliases": null
      },
      {
        "Name": "DefaultProfile",
        "Aliases": [
          "AzContext",
          "AzureRmContext",
          "AzureCredential"
        ]
      },
      {
        "Name": "WhatIf",
        "Aliases": [
          "wi"
        ]
      },
      {
        "Name": "Confirm",
        "Aliases": [
          "cf"
        ]
      }
    ]
  },
  {
    "Command": "Stop-AzCdnEndpoint",
    "IsAlias": false,
    "SourceModule": "Az.Cdn",
    "Version": "1.6.0",
    "Parameters": [
      {
        "Name": "EndpointName",
        "Aliases": null
      },
      {
        "Name": "ProfileName",
        "Aliases": null
      },
      {
        "Name": "ResourceGroupName",
        "Aliases": null
      },
      {
        "Name": "CdnEndpoint",
        "Aliases": null
      },
      {
        "Name": "PassThru",
        "Aliases": null
      },
      {
        "Name": "DefaultProfile",
        "Aliases": [
          "AzContext",
          "AzureRmContext",
          "AzureCredential"
        ]
      },
      {
        "Name": "WhatIf",
        "Aliases": [
          "wi"
        ]
      },
      {
        "Name": "Confirm",
        "Aliases": [
          "cf"
        ]
      }
    ]
  },
  {
    "Command": "Test-AzCdnCustomDomain",
    "IsAlias": false,
    "SourceModule": "Az.Cdn",
    "Version": "1.6.0",
    "Parameters": [
      {
        "Name": "EndpointName",
        "Aliases": null
      },
      {
        "Name": "ProfileName",
        "Aliases": null
      },
      {
        "Name": "ResourceGroupName",
        "Aliases": null
      },
      {
        "Name": "CdnEndpoint",
        "Aliases": null
      },
      {
        "Name": "CustomDomainHostName",
        "Aliases": null
      },
      {
        "Name": "DefaultProfile",
        "Aliases": [
          "AzContext",
          "AzureRmContext",
          "AzureCredential"
        ]
      }
    ]
  },
  {
    "Command": "Get-AzCdnCustomDomain",
    "IsAlias": false,
    "SourceModule": "Az.Cdn",
    "Version": "1.6.0",
    "Parameters": [
      {
        "Name": "CustomDomainName",
        "Aliases": null
      },
      {
        "Name": "EndpointName",
        "Aliases": null
      },
      {
        "Name": "ProfileName",
        "Aliases": null
      },
      {
        "Name": "ResourceGroupName",
        "Aliases": null
      },
      {
        "Name": "CdnEndpoint",
        "Aliases": null
      },
      {
        "Name": "DefaultProfile",
        "Aliases": [
          "AzContext",
          "AzureRmContext",
          "AzureCredential"
        ]
      }
    ]
  },
  {
    "Command": "New-AzCdnCustomDomain",
    "IsAlias": false,
    "SourceModule": "Az.Cdn",
    "Version": "1.6.0",
    "Parameters": [
      {
        "Name": "HostName",
        "Aliases": null
      },
      {
        "Name": "CustomDomainName",
        "Aliases": null
      },
      {
        "Name": "EndpointName",
        "Aliases": null
      },
      {
        "Name": "ProfileName",
        "Aliases": null
      },
      {
        "Name": "ResourceGroupName",
        "Aliases": null
      },
      {
        "Name": "CdnEndpoint",
        "Aliases": null
      },
      {
        "Name": "DefaultProfile",
        "Aliases": [
          "AzContext",
          "AzureRmContext",
          "AzureCredential"
        ]
      },
      {
        "Name": "WhatIf",
        "Aliases": [
          "wi"
        ]
      },
      {
        "Name": "Confirm",
        "Aliases": [
          "cf"
        ]
      }
    ]
  },
  {
    "Command": "Remove-AzCdnCustomDomain",
    "IsAlias": false,
    "SourceModule": "Az.Cdn",
    "Version": "1.6.0",
    "Parameters": [
      {
        "Name": "CustomDomainName",
        "Aliases": null
      },
      {
        "Name": "EndpointName",
        "Aliases": null
      },
      {
        "Name": "ProfileName",
        "Aliases": null
      },
      {
        "Name": "ResourceGroupName",
        "Aliases": null
      },
      {
        "Name": "CdnCustomDomain",
        "Aliases": null
      },
      {
        "Name": "PassThru",
        "Aliases": null
      },
      {
        "Name": "DefaultProfile",
        "Aliases": [
          "AzContext",
          "AzureRmContext",
          "AzureCredential"
        ]
      },
      {
        "Name": "WhatIf",
        "Aliases": [
          "wi"
        ]
      },
      {
        "Name": "Confirm",
        "Aliases": [
          "cf"
        ]
      }
    ]
  },
  {
    "Command": "Enable-AzCdnCustomDomain",
    "IsAlias": false,
    "SourceModule": "Az.Cdn",
    "Version": "1.6.0",
    "Parameters": [
      {
        "Name": "CustomDomainName",
        "Aliases": null
      },
      {
        "Name": "EndpointName",
        "Aliases": null
      },
      {
        "Name": "ProfileName",
        "Aliases": null
      },
      {
        "Name": "ResourceGroupName",
        "Aliases": null
      },
      {
        "Name": "InputObject",
        "Aliases": null
      },
      {
        "Name": "PassThru",
        "Aliases": null
      },
      {
        "Name": "DefaultProfile",
        "Aliases": [
          "AzContext",
          "AzureRmContext",
          "AzureCredential"
        ]
      },
      {
        "Name": "WhatIf",
        "Aliases": [
          "wi"
        ]
      },
      {
        "Name": "Confirm",
        "Aliases": [
          "cf"
        ]
      }
    ]
  },
  {
    "Command": "Disable-AzCdnCustomDomain",
    "IsAlias": false,
    "SourceModule": "Az.Cdn",
    "Version": "1.6.0",
    "Parameters": [
      {
        "Name": "CustomDomainName",
        "Aliases": null
      },
      {
        "Name": "EndpointName",
        "Aliases": null
      },
      {
        "Name": "ProfileName",
        "Aliases": null
      },
      {
        "Name": "ResourceGroupName",
        "Aliases": null
      },
      {
        "Name": "InputObject",
        "Aliases": null
      },
      {
        "Name": "PassThru",
        "Aliases": null
      },
      {
        "Name": "DefaultProfile",
        "Aliases": [
          "AzContext",
          "AzureRmContext",
          "AzureCredential"
        ]
      },
      {
        "Name": "WhatIf",
        "Aliases": [
          "wi"
        ]
      },
      {
        "Name": "Confirm",
        "Aliases": [
          "cf"
        ]
      }
    ]
  },
  {
    "Command": "Enable-AzCdnCustomDomainHttps",
    "IsAlias": false,
    "SourceModule": "Az.Cdn",
    "Version": "1.6.0",
    "Parameters": [
      {
        "Name": "ResourceGroupName",
        "Aliases": null
      },
      {
        "Name": "ProfileName",
        "Aliases": null
      },
      {
        "Name": "EndpointName",
        "Aliases": null
      },
      {
        "Name": "CustomDomainName",
        "Aliases": null
      },
      {
        "Name": "InputObject",
        "Aliases": null
      },
      {
        "Name": "ResourceId",
        "Aliases": null
      },
      {
        "Name": "PassThru",
        "Aliases": null
      },
      {
        "Name": "DefaultProfile",
        "Aliases": [
          "AzContext",
          "AzureRmContext",
          "AzureCredential"
        ]
      },
      {
        "Name": "WhatIf",
        "Aliases": [
          "wi"
        ]
      },
      {
        "Name": "Confirm",
        "Aliases": [
          "cf"
        ]
      }
    ]
  },
  {
    "Command": "Disable-AzCdnCustomDomainHttps",
    "IsAlias": false,
    "SourceModule": "Az.Cdn",
    "Version": "1.6.0",
    "Parameters": [
      {
        "Name": "ResourceGroupName",
        "Aliases": null
      },
      {
        "Name": "ProfileName",
        "Aliases": null
      },
      {
        "Name": "EndpointName",
        "Aliases": null
      },
      {
        "Name": "CustomDomainName",
        "Aliases": null
      },
      {
        "Name": "InputObject",
        "Aliases": null
      },
      {
        "Name": "ResourceId",
        "Aliases": null
      },
      {
        "Name": "PassThru",
        "Aliases": null
      },
      {
        "Name": "DefaultProfile",
        "Aliases": [
          "AzContext",
          "AzureRmContext",
          "AzureCredential"
        ]
      },
      {
        "Name": "WhatIf",
        "Aliases": [
          "wi"
        ]
      },
      {
        "Name": "Confirm",
        "Aliases": [
          "cf"
        ]
      }
    ]
  },
  {
    "Command": "Get-AzCdnProfileResourceUsage",
    "IsAlias": false,
    "SourceModule": "Az.Cdn",
    "Version": "1.6.0",
    "Parameters": [
      {
        "Name": "ProfileName",
        "Aliases": null
      },
      {
        "Name": "ResourceGroupName",
        "Aliases": null
      },
      {
        "Name": "CdnProfile",
        "Aliases": null
      },
      {
        "Name": "DefaultProfile",
        "Aliases": [
          "AzContext",
          "AzureRmContext",
          "AzureCredential"
        ]
      }
    ]
  },
  {
    "Command": "Confirm-AzCdnEndpointProbeUrl",
    "IsAlias": false,
    "SourceModule": "Az.Cdn",
    "Version": "1.6.0",
    "Parameters": [
      {
        "Name": "ProbeUrl",
        "Aliases": null
      },
      {
        "Name": "DefaultProfile",
        "Aliases": [
          "AzContext",
          "AzureRmContext",
          "AzureCredential"
        ]
      }
    ]
  },
  {
    "Command": "Get-AzCdnEndpointResourceUsage",
    "IsAlias": false,
    "SourceModule": "Az.Cdn",
    "Version": "1.6.0",
    "Parameters": [
      {
        "Name": "EndpointName",
        "Aliases": null
      },
      {
        "Name": "ProfileName",
        "Aliases": null
      },
      {
        "Name": "ResourceGroupName",
        "Aliases": null
      },
      {
        "Name": "CdnEndpoint",
        "Aliases": null
      },
      {
        "Name": "DefaultProfile",
        "Aliases": [
          "AzContext",
          "AzureRmContext",
          "AzureCredential"
        ]
      }
    ]
  },
  {
    "Command": "Get-AzCdnProfileSupportedOptimizationType",
    "IsAlias": false,
    "SourceModule": "Az.Cdn",
    "Version": "1.6.0",
    "Parameters": [
      {
        "Name": "ProfileName",
        "Aliases": null
      },
      {
        "Name": "ResourceGroupName",
        "Aliases": null
      },
      {
        "Name": "CdnProfile",
        "Aliases": null
      },
      {
        "Name": "DefaultProfile",
        "Aliases": [
          "AzContext",
          "AzureRmContext",
          "AzureCredential"
        ]
      }
    ]
  },
  {
    "Command": "Get-AzCdnSubscriptionResourceUsage",
    "IsAlias": false,
    "SourceModule": "Az.Cdn",
    "Version": "1.6.0",
    "Parameters": [
      {
        "Name": "DefaultProfile",
        "Aliases": [
          "AzContext",
          "AzureRmContext",
          "AzureCredential"
        ]
      }
    ]
  },
  {
    "Command": "Get-AzCdnEdgeNode",
    "IsAlias": false,
    "SourceModule": "Az.Cdn",
    "Version": "1.6.0",
    "Parameters": [
      {
        "Name": "DefaultProfile",
        "Aliases": [
          "AzContext",
          "AzureRmContext",
          "AzureCredential"
        ]
      }
    ]
  },
  {
    "Command": "New-AzCdnDeliveryRule",
    "IsAlias": false,
    "SourceModule": "Az.Cdn",
    "Version": "1.6.0",
    "Parameters": [
      {
        "Name": "Name",
        "Aliases": null
      },
      {
        "Name": "Order",
        "Aliases": null
      },
      {
        "Name": "Condition",
        "Aliases": null
      },
      {
        "Name": "Action",
        "Aliases": null
      },
      {
        "Name": "DefaultProfile",
        "Aliases": [
          "AzContext",
          "AzureRmContext",
          "AzureCredential"
        ]
      }
    ]
  },
  {
    "Command": "New-AzCdnDeliveryRuleCondition",
    "IsAlias": false,
    "SourceModule": "Az.Cdn",
    "Version": "1.6.0",
    "Parameters": [
      {
        "Name": "MatchVariable",
        "Aliases": null
      },
      {
        "Name": "Operator",
        "Aliases": null
      },
      {
        "Name": "Selector",
        "Aliases": null
      },
      {
        "Name": "MatchValue",
        "Aliases": null
      },
      {
        "Name": "Transform",
        "Aliases": null
      },
      {
        "Name": "NegateCondition",
        "Aliases": null
      },
      {
        "Name": "DefaultProfile",
        "Aliases": [
          "AzContext",
          "AzureRmContext",
          "AzureCredential"
        ]
      }
    ]
  },
  {
    "Command": "New-AzCdnDeliveryRuleAction",
    "IsAlias": false,
    "SourceModule": "Az.Cdn",
    "Version": "1.6.0",
    "Parameters": [
      {
        "Name": "CacheBehavior",
        "Aliases": null
      },
      {
        "Name": "CacheDuration",
        "Aliases": null
      },
      {
        "Name": "HeaderActionType",
        "Aliases": null
      },
      {
        "Name": "Action",
        "Aliases": null
      },
      {
        "Name": "HeaderName",
        "Aliases": null
      },
      {
        "Name": "Value",
        "Aliases": null
      },
      {
        "Name": "RedirectType",
        "Aliases": null
      },
      {
        "Name": "DestinationProtocol",
        "Aliases": null
      },
      {
        "Name": "CustomPath",
        "Aliases": null
      },
      {
        "Name": "CustomHostname",
        "Aliases": null
      },
      {
        "Name": "CustomQueryString",
        "Aliases": null
      },
      {
        "Name": "CustomFragment",
        "Aliases": null
      },
      {
        "Name": "QueryStringBehavior",
        "Aliases": null
      },
      {
        "Name": "QueryParameter",
        "Aliases": null
      },
      {
        "Name": "SourcePattern",
        "Aliases": null
      },
      {
        "Name": "Destination",
        "Aliases": null
      },
      {
        "Name": "PreservePath",
        "Aliases": null
      },
      {
        "Name": "DefaultProfile",
        "Aliases": [
          "AzContext",
          "AzureRmContext",
          "AzureCredential"
        ]
      }
    ]
  },
  {
    "Command": "New-AzCdnDeliveryPolicy",
    "IsAlias": false,
    "SourceModule": "Az.Cdn",
    "Version": "1.6.0",
    "Parameters": [
      {
        "Name": "Description",
        "Aliases": null
      },
      {
        "Name": "Rule",
        "Aliases": null
      },
      {
        "Name": "DefaultProfile",
        "Aliases": [
          "AzContext",
          "AzureRmContext",
          "AzureCredential"
        ]
      }
    ]
  },
  {
    "Command": "New-AzCdnOrigin",
    "IsAlias": false,
    "SourceModule": "Az.Cdn",
    "Version": "1.6.0",
    "Parameters": [
      {
        "Name": "EndpointName",
        "Aliases": null
      },
      {
        "Name": "HostName",
        "Aliases": null
      },
      {
        "Name": "HttpPort",
        "Aliases": null
      },
      {
        "Name": "HttpsPort",
        "Aliases": null
      },
      {
        "Name": "OriginHostHeader",
        "Aliases": null
      },
      {
        "Name": "OriginName",
        "Aliases": null
      },
      {
        "Name": "ProfileName",
        "Aliases": null
      },
      {
        "Name": "Priority",
        "Aliases": null
      },
      {
        "Name": "PrivateLinkApprovalMessage",
        "Aliases": null
      },
      {
        "Name": "PrivateLinkLocation",
        "Aliases": null
      },
      {
        "Name": "PrivateLinkResourceId",
        "Aliases": null
      },
      {
        "Name": "ResourceGroupName",
        "Aliases": null
      },
      {
        "Name": "Weight",
        "Aliases": null
      },
      {
        "Name": "CdnOrigin",
        "Aliases": null
      },
      {
        "Name": "DefaultProfile",
        "Aliases": [
          "AzContext",
          "AzureRmContext",
          "AzureCredential"
        ]
      },
      {
        "Name": "WhatIf",
        "Aliases": [
          "wi"
        ]
      },
      {
        "Name": "Confirm",
        "Aliases": [
          "cf"
        ]
      }
    ]
  },
  {
    "Command": "Remove-AzCdnOrigin",
    "IsAlias": false,
    "SourceModule": "Az.Cdn",
    "Version": "1.6.0",
    "Parameters": [
      {
        "Name": "OriginName",
        "Aliases": null
      },
      {
        "Name": "EndpointName",
        "Aliases": null
      },
      {
        "Name": "ProfileName",
        "Aliases": null
      },
      {
        "Name": "ResourceGroupName",
        "Aliases": null
      },
      {
        "Name": "ResourceId",
        "Aliases": null
      },
      {
        "Name": "PassThru",
        "Aliases": null
      },
      {
        "Name": "CdnOrigin",
        "Aliases": null
      },
      {
        "Name": "DefaultProfile",
        "Aliases": [
          "AzContext",
          "AzureRmContext",
          "AzureCredential"
        ]
      },
      {
        "Name": "WhatIf",
        "Aliases": [
          "wi"
        ]
      },
      {
        "Name": "Confirm",
        "Aliases": [
          "cf"
        ]
      }
    ]
  },
  {
    "Command": "New-AzCdnOriginGroup",
    "IsAlias": false,
    "SourceModule": "Az.Cdn",
    "Version": "1.6.0",
    "Parameters": [
      {
        "Name": "EndpointName",
        "Aliases": null
      },
      {
        "Name": "OriginGroupName",
        "Aliases": null
      },
      {
        "Name": "OriginId",
        "Aliases": null
      },
      {
        "Name": "ProbeIntervalInSeconds",
        "Aliases": null
      },
      {
        "Name": "ProbePath",
        "Aliases": null
      },
      {
        "Name": "ProbeProtocol",
        "Aliases": null
      },
      {
        "Name": "ProbeRequestType",
        "Aliases": null
      },
      {
        "Name": "ProfileName",
        "Aliases": null
      },
      {
        "Name": "ResourceGroupName",
        "Aliases": null
      },
      {
        "Name": "CdnOriginGroup",
        "Aliases": null
      },
      {
        "Name": "DefaultProfile",
        "Aliases": [
          "AzContext",
          "AzureRmContext",
          "AzureCredential"
        ]
      },
      {
        "Name": "WhatIf",
        "Aliases": [
          "wi"
        ]
      },
      {
        "Name": "Confirm",
        "Aliases": [
          "cf"
        ]
      }
    ]
  },
  {
    "Command": "Get-AzCdnOriginGroup",
    "IsAlias": false,
    "SourceModule": "Az.Cdn",
    "Version": "1.6.0",
    "Parameters": [
      {
        "Name": "EndpointName",
        "Aliases": null
      },
      {
        "Name": "OriginGroupName",
        "Aliases": null
      },
      {
        "Name": "ProfileName",
        "Aliases": null
      },
      {
        "Name": "ResourceGroupName",
        "Aliases": null
      },
      {
        "Name": "ResourceId",
        "Aliases": null
      },
      {
        "Name": "DefaultProfile",
        "Aliases": [
          "AzContext",
          "AzureRmContext",
          "AzureCredential"
        ]
      }
    ]
  },
  {
    "Command": "Remove-AzCdnOriginGroup",
    "IsAlias": false,
    "SourceModule": "Az.Cdn",
    "Version": "1.6.0",
    "Parameters": [
      {
        "Name": "OriginGroupName",
        "Aliases": null
      },
      {
        "Name": "EndpointName",
        "Aliases": null
      },
      {
        "Name": "ProfileName",
        "Aliases": null
      },
      {
        "Name": "ResourceGroupName",
        "Aliases": null
      },
      {
        "Name": "ResourceId",
        "Aliases": null
      },
      {
        "Name": "PassThru",
        "Aliases": null
      },
      {
        "Name": "CdnOriginGroup",
        "Aliases": null
      },
      {
        "Name": "DefaultProfile",
        "Aliases": [
          "AzContext",
          "AzureRmContext",
          "AzureCredential"
        ]
      },
      {
        "Name": "WhatIf",
        "Aliases": [
          "wi"
        ]
      },
      {
        "Name": "Confirm",
        "Aliases": [
          "cf"
        ]
      }
    ]
  },
  {
    "Command": "Set-AzCdnOriginGroup",
    "IsAlias": false,
    "SourceModule": "Az.Cdn",
    "Version": "1.6.0",
    "Parameters": [
      {
        "Name": "EndpointName",
        "Aliases": null
      },
      {
        "Name": "OriginGroupName",
        "Aliases": null
      },
      {
        "Name": "OriginId",
        "Aliases": null
      },
      {
        "Name": "ProbeIntervalInSeconds",
        "Aliases": null
      },
      {
        "Name": "ProbePath",
        "Aliases": null
      },
      {
        "Name": "ProbeProtocol",
        "Aliases": null
      },
      {
        "Name": "ProbeRequestType",
        "Aliases": null
      },
      {
        "Name": "ProfileName",
        "Aliases": null
      },
      {
        "Name": "ResourceGroupName",
        "Aliases": null
      },
      {
        "Name": "CdnOriginGroup",
        "Aliases": null
      },
      {
        "Name": "DefaultProfile",
        "Aliases": [
          "AzContext",
          "AzureRmContext",
          "AzureCredential"
        ]
      },
      {
        "Name": "WhatIf",
        "Aliases": [
          "wi"
        ]
      },
      {
        "Name": "Confirm",
        "Aliases": [
          "cf"
        ]
      }
    ]
  },
  {
    "Command": "Validate-AzCdnCustomDomain",
    "IsAlias": false,
    "SourceModule": "Az.Cdn",
    "Version": "1.6.0",
    "Parameters": [
      {
        "Name": "EndpointName",
        "Aliases": null
      },
      {
        "Name": "ProfileName",
        "Aliases": null
      },
      {
        "Name": "ResourceGroupName",
        "Aliases": null
      },
      {
        "Name": "CdnEndpoint",
        "Aliases": null
      },
      {
        "Name": "CustomDomainHostName",
        "Aliases": null
      },
      {
        "Name": "DefaultProfile",
        "Aliases": [
          "AzContext",
          "AzureRmContext",
          "AzureCredential"
        ]
      }
    ]
  },
  {
    "Command": "Get-AzCdnEdgeNodes",
    "IsAlias": false,
    "SourceModule": "Az.Cdn",
    "Version": "1.6.0",
    "Parameters": [
      {
        "Name": "DefaultProfile",
        "Aliases": [
          "AzContext",
          "AzureRmContext",
          "AzureCredential"
        ]
      }
    ]
  }
]
